<?xml version="1.0" encoding="utf-8" ?>
<odoo>
    <record id="action_repair_config_settings" model="ir.actions.act_window">
        <field name="name">Settings</field>
        <field name="res_model">res.config.settings</field>
        <field name="view_mode">form</field>
        <field name="target">inline</field>
        <field name="context">{'module': 'repair', 'bin_size': False}</field>
    </record>

    <menuitem
        id="menu_repair_config_settings"
        name="Settings"
        parent="repair.repair_menu_config"
        action="action_repair_config_settings"
        sequence="99"
        groups="stock.group_stock_manager"
    />
</odoo>
